[
    {
        "identifiers": ["uuid:ee65c136-382d-4aee-b988-21d97aa250f0"],
        "name": "Nasdanika",
        "icon": "https://docs.nasdanika.org/images/nasdanika-logo.png",
        "location": "https://www.nasdanika.org",
        "type": {
            "name": "Action",
            "ns-uri": "ecore://nasdanika.org/html/app"
        }
    },
    {
        "container": {
            "reference": "children",
            "identifiers": ["uuid:ee65c136-382d-4aee-b988-21d97aa250f0"]
        },
        "identifiers": ["uuid:53f0f8e0-9252-4d04-9292-a7e722259976"],
        "name": "Test Models Documentation",
        "icon": "fa fa-book",
        "location": "index.html",
        "type": {
            "name": "Action",
            "ns-uri": "ecore://nasdanika.org/html/app"
        }
    },
    {
        "container": {
            "reference": "children",
            "identifiers": ["uuid:ee65c136-382d-4aee-b988-21d97aa250f0"]
        },
        "identifiers": ["uuid:9484085d-7d57-4d40-8339-a02914524bf7"],
        "name": "Search",
        "icon": "fas fa-search",
        "location": "search.html",
        "type": {
            "name": "Action",
            "ns-uri": "ecore://nasdanika.org/html/app"
        }
    },
    {
        "container": {
            "reference": "children",
            "identifiers": ["uuid:ee65c136-382d-4aee-b988-21d97aa250f0"]
        },
        "identifiers": ["uuid:7d26b684-7986-4f17-b617-514a49b16f78"],
        "name": "Glossary",
        "icon": "fas fa-book",
        "location": "glossary.html",
        "type": {
            "name": "Action",
            "ns-uri": "ecore://nasdanika.org/html/app"
        }
    },
    {
        "identifiers": ["ecore://test.ecore-gen.html.nasdanika.org"],
        "name": "Trum",
        "icon": "fas fa-users",
        "description": "My description",
        "location": "test/index.html",
        "type": {
            "name": "EPackage",
            "ns-uri": "http://www.eclipse.org/emf/2002/Ecore"
        }
    },
    {
        "container": {
            "reference": "eClassifiers",
            "identifiers": ["ecore://test.ecore-gen.html.nasdanika.org"]
        },
        "identifiers": ["ecore://test.ecore-gen.html.nasdanika.org/eClassifiers/Animal"],
        "name": "Животное",
        "icon": "https://cdn.jsdelivr.net/gh/Nasdanika-Models/ecore@master/graph/web-resources/icons/EClass.gif",
        "description": "Животные относятся к эукариотам (в клетках имеются ядра). Классическими признаками животных считаются: гетеротрофность (питание готовыми органическими соединениями) и способность активно передвигаться.",
        "location": "test/references/eClassifiers/Animal/index.html",
        "type": {
            "name": "EClass",
            "ns-uri": "http://www.eclipse.org/emf/2002/Ecore"
        }
    },
    {
        "container": {
            "reference": "navigation",
            "identifiers": ["uuid:d56d94f1-8290-4314-814d-0c72347a4e6c"]
        },
        "identifiers": ["uuid:a0c06a32-b48e-420f-8161-0049cbe79b37"],
        "name": "Attributes",
        "icon": "https://cdn.jsdelivr.net/gh/Nasdanika-Models/ecore@master/graph/web-resources/icons/EAttribute.gif",
        "location": "test/references/eClassifiers/Animal/attributes.html",
        "type": {
            "name": "Action",
            "ns-uri": "ecore://nasdanika.org/html/app"
        }
    },
    {
        "container": {
            "reference": "eStructuralFeatures",
            "identifiers": ["ecore://test.ecore-gen.html.nasdanika.org/eClassifiers/Animal"]
        },
        "identifiers": ["ecore://test.ecore-gen.html.nasdanika.org/eClassifiers/Animal/eStructuralFeatures/name"],
        "name": "Имя",
        "icon": "https://cdn.jsdelivr.net/gh/Nasdanika-Models/ecore@master/graph/web-resources/icons/EAttribute.gif",
        "description": "Имя животного, например 'Мурзик'",
        "location": "test/references/eClassifiers/Animal/references/eStructuralFeatures/name/index.html",
        "type": {
            "name": "EAttribute",
            "ns-uri": "http://www.eclipse.org/emf/2002/Ecore"
        }
    },
    {
        "container": {
            "reference": "navigation",
            "identifiers": ["uuid:d56d94f1-8290-4314-814d-0c72347a4e6c"]
        },
        "identifiers": ["uuid:504cb4c4-f3cf-4208-982d-efedc4509995"],
        "name": "Inheritance",
        "icon": "https://cdn.jsdelivr.net/gh/Nasdanika-Models/ecore@master/graph/web-resources/icons/EGenericSuperType.gif",
        "location": "test/references/eClassifiers/Animal/inheritance.html",
        "type": {
            "name": "Action",
            "ns-uri": "ecore://nasdanika.org/html/app"
        }
    },
    {
        "container": {
            "reference": "sections",
            "identifiers": ["uuid:504cb4c4-f3cf-4208-982d-efedc4509995"]
        },
        "identifiers": ["uuid:858e9822-7e11-4003-86c3-fb3ff4e7cf6f"],
        "name": "Supertypes",
        "location": "test/references/eClassifiers/Animal/inheritance.html#uuid-858e9822-7e11-4003-86c3-fb3ff4e7cf6f",
        "type": {
            "name": "Action",
            "ns-uri": "ecore://nasdanika.org/html/app"
        }
    },
    {
        "container": {
            "reference": "sections",
            "identifiers": ["uuid:504cb4c4-f3cf-4208-982d-efedc4509995"]
        },
        "identifiers": ["uuid:d8b1d351-dd9f-4c4e-9970-117bbeaab146"],
        "name": "Subtypes",
        "location": "test/references/eClassifiers/Animal/inheritance.html#uuid-d8b1d351-dd9f-4c4e-9970-117bbeaab146",
        "type": {
            "name": "Action",
            "ns-uri": "ecore://nasdanika.org/html/app"
        }
    },
    {
        "container": {
            "reference": "navigation",
            "identifiers": ["uuid:d56d94f1-8290-4314-814d-0c72347a4e6c"]
        },
        "identifiers": ["uuid:6f30754b-39fe-4a0a-8532-6bc227207a31"],
        "name": "Operations",
        "icon": "https://cdn.jsdelivr.net/gh/Nasdanika-Models/ecore@master/graph/web-resources/icons/EOperation.gif",
        "location": "test/references/eClassifiers/Animal/operations.html",
        "type": {
            "name": "Action",
            "ns-uri": "ecore://nasdanika.org/html/app"
        }
    },
    {
        "container": {
            "reference": "eOperations",
            "identifiers": ["ecore://test.ecore-gen.html.nasdanika.org/eClassifiers/Animal"]
        },
        "identifiers": ["ecore://test.ecore-gen.html.nasdanika.org/eClassifiers/Animal/eOperations/eats"],
        "name": "Ест",
        "icon": "https://cdn.jsdelivr.net/gh/Nasdanika-Models/ecore@master/graph/web-resources/icons/EOperation.gif",
        "location": "test/references/eClassifiers/Animal/references/eOperations/eats-1/index.html",
        "type": {
            "name": "EOperation",
            "ns-uri": "http://www.eclipse.org/emf/2002/Ecore"
        }
    },
    {
        "container": {
            "reference": "navigation",
            "identifiers": ["uuid:661958fe-7f11-4deb-8ac1-3c3c2ea696bc"]
        },
        "identifiers": ["uuid:3ce37908-191f-49df-bf1f-7573baec6ea5"],
        "name": "Parameters",
        "icon": "https://cdn.jsdelivr.net/gh/Nasdanika-Models/ecore@master/graph/web-resources/icons/EParameter.gif",
        "location": "test/references/eClassifiers/Animal/references/eOperations/eats-1/parameters.html",
        "type": {
            "name": "Action",
            "ns-uri": "ecore://nasdanika.org/html/app"
        }
    },
    {
        "container": {
            "reference": "eParameters",
            "identifiers": ["ecore://test.ecore-gen.html.nasdanika.org/eClassifiers/Animal/eOperations/eats"]
        },
        "identifiers": ["ecore://test.ecore-gen.html.nasdanika.org/eClassifiers/Animal/eOperations/eats/eParameters/food"],
        "name": "пища",
        "icon": "https://cdn.jsdelivr.net/gh/Nasdanika-Models/ecore@master/graph/web-resources/icons/EParameter.gif",
        "description": "Food which animal eats",
        "location": "test/references/eClassifiers/Animal/references/eOperations/eats-1/references/eParameters/food/index.html",
        "type": {
            "name": "EParameter",
            "ns-uri": "http://www.eclipse.org/emf/2002/Ecore"
        }
    },
    {
        "container": {
            "reference": "navigation",
            "identifiers": ["uuid:d56d94f1-8290-4314-814d-0c72347a4e6c"]
        },
        "identifiers": ["uuid:e37cd171-9d19-4168-9f9c-fc98e70fec14"],
        "name": "Type Parameters",
        "icon": "https://cdn.jsdelivr.net/gh/Nasdanika-Models/ecore@master/graph/web-resources/icons/ETypeParameter.gif",
        "location": "test/references/eClassifiers/Animal/type-parameters.html",
        "type": {
            "name": "Action",
            "ns-uri": "ecore://nasdanika.org/html/app"
        }
    },
    {
        "container": {
            "reference": "eTypeParameters",
            "identifiers": ["ecore://test.ecore-gen.html.nasdanika.org/eClassifiers/Animal"]
        },
        "identifiers": ["ecore://test.ecore-gen.html.nasdanika.org/eClassifiers/Animal/eTypeParameters/F"],
        "name": "Пища",
        "icon": "https://cdn.jsdelivr.net/gh/Nasdanika-Models/ecore@master/graph/web-resources/icons/ETypeParameter.gif",
        "description": "Food which animal eats",
        "location": "test/references/eClassifiers/Animal/references/eTypeParameters/F/index.html",
        "type": {
            "name": "ETypeParameter",
            "ns-uri": "http://www.eclipse.org/emf/2002/Ecore"
        }
    },
    {
        "container": {
            "reference": "navigation",
            "identifiers": ["uuid:8887ad6a-30d4-454e-b7fd-871c3a360a66"]
        },
        "identifiers": ["uuid:2b58e2cb-0679-4b09-b6db-116cd47f91a3"],
        "name": "Bounds",
        "icon": "https://cdn.jsdelivr.net/gh/Nasdanika-Models/ecore@master/graph/web-resources/icons/EGenericType.gif",
        "location": "test/references/eClassifiers/Animal/references/eTypeParameters/F/bounds.html",
        "type": {
            "name": "Action",
            "ns-uri": "ecore://nasdanika.org/html/app"
        }
    },
    {
        "container": {
            "reference": "eBounds",
            "identifiers": ["ecore://test.ecore-gen.html.nasdanika.org/eClassifiers/Animal/eTypeParameters/F"]
        },
        "identifiers": ["ecore://test.ecore-gen.html.nasdanika.org/eClassifiers/Animal/eTypeParameters/F/e-bounds/0"],
        "name": "Hmmm",
        "description": "Hmmm description",
        "location": "test/references/eClassifiers/Animal/references/eTypeParameters/F/references/eBounds/0/index.html",
        "type": {
            "name": "EGenericType",
            "ns-uri": "http://www.eclipse.org/emf/2002/Ecore"
        }
    },
    {
        "container": {
            "reference": "eClassifiers",
            "identifiers": ["ecore://test.ecore-gen.html.nasdanika.org"]
        },
        "identifiers": ["ecore://test.ecore-gen.html.nasdanika.org/eClassifiers/Biome"],
        "name": "Biome",
        "icon": "https://cdn.jsdelivr.net/gh/Nasdanika-Models/ecore@master/graph/web-resources/icons/EClass.gif",
        "location": "test/references/eClassifiers/Biome/index.html",
        "type": {
            "name": "EClass",
            "ns-uri": "http://www.eclipse.org/emf/2002/Ecore"
        }
    },
    {
        "container": {
            "reference": "navigation",
            "identifiers": ["uuid:5f6963c1-bfb3-4de8-8f4a-b8bf58a15abe"]
        },
        "identifiers": ["uuid:e7fb3d45-c826-4d6a-9507-a75d7cd7b19b"],
        "name": "References",
        "icon": "https://cdn.jsdelivr.net/gh/Nasdanika-Models/ecore@master/graph/web-resources/icons/EReference.gif",
        "location": "test/references/eClassifiers/Biome/references.html",
        "type": {
            "name": "Action",
            "ns-uri": "ecore://nasdanika.org/html/app"
        }
    },
    {
        "container": {
            "reference": "navigation",
            "identifiers": ["uuid:5f6963c1-bfb3-4de8-8f4a-b8bf58a15abe"]
        },
        "identifiers": ["uuid:b52e8ac4-af82-47e4-9487-70ce9c068fae"],
        "name": "Inheritance",
        "icon": "https://cdn.jsdelivr.net/gh/Nasdanika-Models/ecore@master/graph/web-resources/icons/EGenericSuperType.gif",
        "location": "test/references/eClassifiers/Biome/inheritance.html",
        "type": {
            "name": "Action",
            "ns-uri": "ecore://nasdanika.org/html/app"
        }
    },
    {
        "container": {
            "reference": "sections",
            "identifiers": ["uuid:b52e8ac4-af82-47e4-9487-70ce9c068fae"]
        },
        "identifiers": ["uuid:5f31a8e3-a2a6-4dac-877b-ca74bc93eaec"],
        "name": "Subtypes",
        "location": "test/references/eClassifiers/Biome/inheritance.html#uuid-5f31a8e3-a2a6-4dac-877b-ca74bc93eaec",
        "type": {
            "name": "Action",
            "ns-uri": "ecore://nasdanika.org/html/app"
        }
    },
    {
        "container": {
            "reference": "eClassifiers",
            "identifiers": ["ecore://test.ecore-gen.html.nasdanika.org"]
        },
        "identifiers": ["ecore://test.ecore-gen.html.nasdanika.org/eClassifiers/Color"],
        "name": "Цвет",
        "icon": "https://cdn.jsdelivr.net/gh/Nasdanika-Models/ecore@master/graph/web-resources/icons/EEnum.gif",
        "description": "Цвет животного",
        "location": "test/references/eClassifiers/Color/index.html",
        "type": {
            "name": "EEnum",
            "ns-uri": "http://www.eclipse.org/emf/2002/Ecore"
        }
    },
    {
        "container": {
            "reference": "eLiterals",
            "identifiers": ["ecore://test.ecore-gen.html.nasdanika.org/eClassifiers/Color"]
        },
        "identifiers": ["ecore://test.ecore-gen.html.nasdanika.org/eClassifiers/Color/eLiterals/White"],
        "name": "Белый",
        "icon": "https://cdn.jsdelivr.net/gh/Nasdanika-Models/ecore@master/graph/web-resources/icons/EEnumLiteral.gif",
        "description": "White color",
        "location": "test/references/eClassifiers/Color/references/eLiterals/White/index.html",
        "type": {
            "name": "EEnumLiteral",
            "ns-uri": "http://www.eclipse.org/emf/2002/Ecore"
        }
    },
    {
        "container": {
            "reference": "eClassifiers",
            "identifiers": ["ecore://test.ecore-gen.html.nasdanika.org"]
        },
        "identifiers": ["ecore://test.ecore-gen.html.nasdanika.org/eClassifiers/Food"],
        "name": "Food",
        "icon": "https://cdn.jsdelivr.net/gh/Nasdanika-Models/ecore@master/graph/web-resources/icons/EInterface.gif",
        "location": "test/references/eClassifiers/Food/index.html",
        "type": {
            "name": "EClass",
            "ns-uri": "http://www.eclipse.org/emf/2002/Ecore"
        }
    },
    {
        "container": {
            "reference": "navigation",
            "identifiers": ["uuid:3330d5a5-c778-4628-abe2-77e70aded38c"]
        },
        "identifiers": ["uuid:f36f01a0-1eab-425f-93c3-811af831d65e"],
        "name": "Inheritance",
        "icon": "https://cdn.jsdelivr.net/gh/Nasdanika-Models/ecore@master/graph/web-resources/icons/EGenericSuperType.gif",
        "location": "test/references/eClassifiers/Food/inheritance.html",
        "type": {
            "name": "Action",
            "ns-uri": "ecore://nasdanika.org/html/app"
        }
    },
    {
        "container": {
            "reference": "sections",
            "identifiers": ["uuid:f36f01a0-1eab-425f-93c3-811af831d65e"]
        },
        "identifiers": ["uuid:735340a7-d13f-463d-a4a0-ea900275b3cc"],
        "name": "Subtypes",
        "location": "test/references/eClassifiers/Food/inheritance.html#uuid-735340a7-d13f-463d-a4a0-ea900275b3cc",
        "type": {
            "name": "Action",
            "ns-uri": "ecore://nasdanika.org/html/app"
        }
    },
    {
        "container": {
            "reference": "eClassifiers",
            "identifiers": ["ecore://test.ecore-gen.html.nasdanika.org"]
        },
        "identifiers": ["ecore://test.ecore-gen.html.nasdanika.org/eClassifiers/Forest"],
        "name": "Forest",
        "icon": "https://cdn.jsdelivr.net/gh/Nasdanika-Models/ecore@master/graph/web-resources/icons/EClass.gif",
        "location": "test/references/eClassifiers/Forest/index.html",
        "type": {
            "name": "EClass",
            "ns-uri": "http://www.eclipse.org/emf/2002/Ecore"
        }
    },
    {
        "container": {
            "reference": "navigation",
            "identifiers": ["uuid:fc775627-437f-4137-b935-2f281cbad6b2"]
        },
        "identifiers": ["uuid:1a91f74b-23e5-4779-abbc-58a434ba6e57"],
        "name": "Inheritance",
        "icon": "https://cdn.jsdelivr.net/gh/Nasdanika-Models/ecore@master/graph/web-resources/icons/EGenericSuperType.gif",
        "location": "test/references/eClassifiers/Forest/inheritance.html",
        "type": {
            "name": "Action",
            "ns-uri": "ecore://nasdanika.org/html/app"
        }
    },
    {
        "container": {
            "reference": "sections",
            "identifiers": ["uuid:1a91f74b-23e5-4779-abbc-58a434ba6e57"]
        },
        "identifiers": ["uuid:118be8a1-9e9c-476a-b057-9e4c96fbae96"],
        "name": "Supertypes",
        "location": "test/references/eClassifiers/Forest/inheritance.html#uuid-118be8a1-9e9c-476a-b057-9e4c96fbae96",
        "type": {
            "name": "Action",
            "ns-uri": "ecore://nasdanika.org/html/app"
        }
    },
    {
        "container": {
            "reference": "navigation",
            "identifiers": ["uuid:fc775627-437f-4137-b935-2f281cbad6b2"]
        },
        "identifiers": ["uuid:dd73e6e0-8c8a-41e0-8bce-656b318e178e"],
        "name": "References",
        "icon": "https://cdn.jsdelivr.net/gh/Nasdanika-Models/ecore@master/graph/web-resources/icons/EReference.gif",
        "location": "test/references/eClassifiers/Forest/references.html",
        "type": {
            "name": "Action",
            "ns-uri": "ecore://nasdanika.org/html/app"
        }
    },
    {
        "container": {
            "reference": "eClassifiers",
            "identifiers": ["ecore://test.ecore-gen.html.nasdanika.org"]
        },
        "identifiers": ["ecore://test.ecore-gen.html.nasdanika.org/eClassifiers/Fox"],
        "name": "Fox",
        "icon": "https://cdn.jsdelivr.net/gh/Nasdanika-Models/ecore@master/graph/web-resources/icons/EClass.gif",
        "location": "test/references/eClassifiers/Fox/index.html",
        "type": {
            "name": "EClass",
            "ns-uri": "http://www.eclipse.org/emf/2002/Ecore"
        }
    },
    {
        "container": {
            "reference": "navigation",
            "identifiers": ["uuid:5c51e143-7b66-4ba2-bd46-2ee8dc84ded2"]
        },
        "identifiers": ["uuid:3104d347-d6a0-475e-8a48-4ede35792cde"],
        "name": "Attributes",
        "icon": "https://cdn.jsdelivr.net/gh/Nasdanika-Models/ecore@master/graph/web-resources/icons/EAttribute.gif",
        "location": "test/references/eClassifiers/Fox/attributes.html",
        "type": {
            "name": "Action",
            "ns-uri": "ecore://nasdanika.org/html/app"
        }
    },
    {
        "container": {
            "reference": "navigation",
            "identifiers": ["uuid:5c51e143-7b66-4ba2-bd46-2ee8dc84ded2"]
        },
        "identifiers": ["uuid:db989659-d2c6-49a3-91d9-7326292c1204"],
        "name": "Inheritance",
        "icon": "https://cdn.jsdelivr.net/gh/Nasdanika-Models/ecore@master/graph/web-resources/icons/EGenericSuperType.gif",
        "location": "test/references/eClassifiers/Fox/inheritance.html",
        "type": {
            "name": "Action",
            "ns-uri": "ecore://nasdanika.org/html/app"
        }
    },
    {
        "container": {
            "reference": "sections",
            "identifiers": ["uuid:db989659-d2c6-49a3-91d9-7326292c1204"]
        },
        "identifiers": ["uuid:847bf1c8-cad4-409a-8667-130d78f0925f"],
        "name": "Supertypes",
        "location": "test/references/eClassifiers/Fox/inheritance.html#uuid-847bf1c8-cad4-409a-8667-130d78f0925f",
        "type": {
            "name": "Action",
            "ns-uri": "ecore://nasdanika.org/html/app"
        }
    },
    {
        "container": {
            "reference": "navigation",
            "identifiers": ["uuid:5c51e143-7b66-4ba2-bd46-2ee8dc84ded2"]
        },
        "identifiers": ["uuid:a9810a66-93c7-4a35-a575-e1c72382dbdb"],
        "name": "Operations",
        "icon": "https://cdn.jsdelivr.net/gh/Nasdanika-Models/ecore@master/graph/web-resources/icons/EOperation.gif",
        "location": "test/references/eClassifiers/Fox/operations.html",
        "type": {
            "name": "Action",
            "ns-uri": "ecore://nasdanika.org/html/app"
        }
    },
    {
        "container": {
            "reference": "eClassifiers",
            "identifiers": ["ecore://test.ecore-gen.html.nasdanika.org"]
        },
        "identifiers": ["ecore://test.ecore-gen.html.nasdanika.org/eClassifiers/Grass"],
        "name": "Grass",
        "icon": "https://cdn.jsdelivr.net/gh/Nasdanika-Models/ecore@master/graph/web-resources/icons/EClass.gif",
        "location": "test/references/eClassifiers/Grass/index.html",
        "type": {
            "name": "EClass",
            "ns-uri": "http://www.eclipse.org/emf/2002/Ecore"
        }
    },
    {
        "container": {
            "reference": "navigation",
            "identifiers": ["uuid:96faaff8-617d-4cf6-8c46-3150014043e6"]
        },
        "identifiers": ["uuid:65792f95-66d2-4d86-8e03-7a01d3eaf6bc"],
        "name": "Attributes",
        "icon": "https://cdn.jsdelivr.net/gh/Nasdanika-Models/ecore@master/graph/web-resources/icons/EAttribute.gif",
        "location": "test/references/eClassifiers/Grass/attributes.html",
        "type": {
            "name": "Action",
            "ns-uri": "ecore://nasdanika.org/html/app"
        }
    },
    {
        "container": {
            "reference": "navigation",
            "identifiers": ["uuid:96faaff8-617d-4cf6-8c46-3150014043e6"]
        },
        "identifiers": ["uuid:aa958213-3193-4b85-91b2-50bb66855cd7"],
        "name": "Inheritance",
        "icon": "https://cdn.jsdelivr.net/gh/Nasdanika-Models/ecore@master/graph/web-resources/icons/EGenericSuperType.gif",
        "location": "test/references/eClassifiers/Grass/inheritance.html",
        "type": {
            "name": "Action",
            "ns-uri": "ecore://nasdanika.org/html/app"
        }
    },
    {
        "container": {
            "reference": "sections",
            "identifiers": ["uuid:aa958213-3193-4b85-91b2-50bb66855cd7"]
        },
        "identifiers": ["uuid:b6514616-a0b2-450f-8bd7-3c2b413186e2"],
        "name": "Supertypes",
        "location": "test/references/eClassifiers/Grass/inheritance.html#uuid-b6514616-a0b2-450f-8bd7-3c2b413186e2",
        "type": {
            "name": "Action",
            "ns-uri": "ecore://nasdanika.org/html/app"
        }
    },
    {
        "container": {
            "reference": "navigation",
            "identifiers": ["uuid:96faaff8-617d-4cf6-8c46-3150014043e6"]
        },
        "identifiers": ["uuid:89220709-503c-44cf-ad0b-d2c68e26c256"],
        "name": "Operations",
        "icon": "https://cdn.jsdelivr.net/gh/Nasdanika-Models/ecore@master/graph/web-resources/icons/EOperation.gif",
        "location": "test/references/eClassifiers/Grass/operations.html",
        "type": {
            "name": "Action",
            "ns-uri": "ecore://nasdanika.org/html/app"
        }
    },
    {
        "container": {
            "reference": "eClassifiers",
            "identifiers": ["ecore://test.ecore-gen.html.nasdanika.org"]
        },
        "identifiers": ["ecore://test.ecore-gen.html.nasdanika.org/eClassifiers/Hare"],
        "name": "Зайка",
        "icon": "https://img.icons8.com/fluency-systems-regular/16/rabbit.svg",
        "description": "Зайка-попрыгайка",
        "location": "test/references/eClassifiers/Hare/index.html",
        "type": {
            "name": "EClass",
            "ns-uri": "http://www.eclipse.org/emf/2002/Ecore"
        }
    },
    {
        "container": {
            "reference": "navigation",
            "identifiers": ["uuid:48c05030-6c89-4036-9e5e-d64e93b1ed24"]
        },
        "identifiers": ["uuid:d61ea7eb-1fab-4c73-be61-739c73a3b5f5"],
        "name": "Attributes",
        "icon": "https://cdn.jsdelivr.net/gh/Nasdanika-Models/ecore@master/graph/web-resources/icons/EAttribute.gif",
        "location": "test/references/eClassifiers/Hare/attributes.html",
        "type": {
            "name": "Action",
            "ns-uri": "ecore://nasdanika.org/html/app"
        }
    },
    {
        "container": {
            "reference": "navigation",
            "identifiers": ["uuid:48c05030-6c89-4036-9e5e-d64e93b1ed24"]
        },
        "identifiers": ["uuid:b78b2169-2e1f-482d-91b9-a608afc4c5b3"],
        "name": "Inheritance",
        "icon": "https://cdn.jsdelivr.net/gh/Nasdanika-Models/ecore@master/graph/web-resources/icons/EGenericSuperType.gif",
        "location": "test/references/eClassifiers/Hare/inheritance.html",
        "type": {
            "name": "Action",
            "ns-uri": "ecore://nasdanika.org/html/app"
        }
    },
    {
        "container": {
            "reference": "sections",
            "identifiers": ["uuid:b78b2169-2e1f-482d-91b9-a608afc4c5b3"]
        },
        "identifiers": ["uuid:22629ddc-5920-4dc3-b905-938a15721856"],
        "name": "Supertypes",
        "location": "test/references/eClassifiers/Hare/inheritance.html#uuid-22629ddc-5920-4dc3-b905-938a15721856",
        "type": {
            "name": "Action",
            "ns-uri": "ecore://nasdanika.org/html/app"
        }
    },
    {
        "container": {
            "reference": "navigation",
            "identifiers": ["uuid:48c05030-6c89-4036-9e5e-d64e93b1ed24"]
        },
        "identifiers": ["uuid:501e3bb5-e82c-4fcd-9de3-5e792fad335d"],
        "name": "Operations",
        "icon": "https://cdn.jsdelivr.net/gh/Nasdanika-Models/ecore@master/graph/web-resources/icons/EOperation.gif",
        "location": "test/references/eClassifiers/Hare/operations.html",
        "type": {
            "name": "Action",
            "ns-uri": "ecore://nasdanika.org/html/app"
        }
    },
    {
        "container": {
            "reference": "eClassifiers",
            "identifiers": ["ecore://test.ecore-gen.html.nasdanika.org"]
        },
        "identifiers": ["ecore://test.ecore-gen.html.nasdanika.org/eClassifiers/LivingBeing"],
        "name": "LivingBeing",
        "icon": "https://cdn.jsdelivr.net/gh/Nasdanika-Models/ecore@master/graph/web-resources/icons/EClass.gif",
        "location": "test/references/eClassifiers/LivingBeing/index.html",
        "type": {
            "name": "EClass",
            "ns-uri": "http://www.eclipse.org/emf/2002/Ecore"
        }
    },
    {
        "container": {
            "reference": "navigation",
            "identifiers": ["uuid:838b9a13-1a49-43a1-a331-991096568248"]
        },
        "identifiers": ["uuid:0caf1130-031a-4f62-b7a5-cd3e36d2e862"],
        "name": "Attributes",
        "icon": "https://cdn.jsdelivr.net/gh/Nasdanika-Models/ecore@master/graph/web-resources/icons/EAttribute.gif",
        "location": "test/references/eClassifiers/LivingBeing/attributes.html",
        "type": {
            "name": "Action",
            "ns-uri": "ecore://nasdanika.org/html/app"
        }
    },
    {
        "container": {
            "reference": "navigation",
            "identifiers": ["uuid:838b9a13-1a49-43a1-a331-991096568248"]
        },
        "identifiers": ["uuid:faa096e8-dea8-484b-9fb8-f061cc0afa36"],
        "name": "Operations",
        "icon": "https://cdn.jsdelivr.net/gh/Nasdanika-Models/ecore@master/graph/web-resources/icons/EOperation.gif",
        "location": "test/references/eClassifiers/LivingBeing/operations.html",
        "type": {
            "name": "Action",
            "ns-uri": "ecore://nasdanika.org/html/app"
        }
    },
    {
        "container": {
            "reference": "navigation",
            "identifiers": ["uuid:838b9a13-1a49-43a1-a331-991096568248"]
        },
        "identifiers": ["uuid:161291e9-71f0-488e-9bb1-82f3e91ef18f"],
        "name": "Inheritance",
        "icon": "https://cdn.jsdelivr.net/gh/Nasdanika-Models/ecore@master/graph/web-resources/icons/EGenericSuperType.gif",
        "location": "test/references/eClassifiers/LivingBeing/inheritance.html",
        "type": {
            "name": "Action",
            "ns-uri": "ecore://nasdanika.org/html/app"
        }
    },
    {
        "container": {
            "reference": "sections",
            "identifiers": ["uuid:161291e9-71f0-488e-9bb1-82f3e91ef18f"]
        },
        "identifiers": ["uuid:9b49b519-bdbc-42db-aead-7f81bb2f50f8"],
        "name": "Subtypes",
        "location": "test/references/eClassifiers/LivingBeing/inheritance.html#uuid-9b49b519-bdbc-42db-aead-7f81bb2f50f8",
        "type": {
            "name": "Action",
            "ns-uri": "ecore://nasdanika.org/html/app"
        }
    },
    {
        "container": {
            "reference": "eClassifiers",
            "identifiers": ["ecore://test.ecore-gen.html.nasdanika.org"]
        },
        "identifiers": ["ecore://test.ecore-gen.html.nasdanika.org/eClassifiers/Plant"],
        "name": "Plant",
        "icon": "https://cdn.jsdelivr.net/gh/Nasdanika-Models/ecore@master/graph/web-resources/icons/EClass.gif",
        "location": "test/references/eClassifiers/Plant/index.html",
        "type": {
            "name": "EClass",
            "ns-uri": "http://www.eclipse.org/emf/2002/Ecore"
        }
    },
    {
        "container": {
            "reference": "navigation",
            "identifiers": ["uuid:5261066d-12d4-4c76-953a-55d2723224af"]
        },
        "identifiers": ["uuid:3db05a06-f72b-482a-b249-009b8d58e545"],
        "name": "Attributes",
        "icon": "https://cdn.jsdelivr.net/gh/Nasdanika-Models/ecore@master/graph/web-resources/icons/EAttribute.gif",
        "location": "test/references/eClassifiers/Plant/attributes.html",
        "type": {
            "name": "Action",
            "ns-uri": "ecore://nasdanika.org/html/app"
        }
    },
    {
        "container": {
            "reference": "navigation",
            "identifiers": ["uuid:5261066d-12d4-4c76-953a-55d2723224af"]
        },
        "identifiers": ["uuid:c66c5ee7-378b-4e64-9040-74a29396307c"],
        "name": "Inheritance",
        "icon": "https://cdn.jsdelivr.net/gh/Nasdanika-Models/ecore@master/graph/web-resources/icons/EGenericSuperType.gif",
        "location": "test/references/eClassifiers/Plant/inheritance.html",
        "type": {
            "name": "Action",
            "ns-uri": "ecore://nasdanika.org/html/app"
        }
    },
    {
        "container": {
            "reference": "sections",
            "identifiers": ["uuid:c66c5ee7-378b-4e64-9040-74a29396307c"]
        },
        "identifiers": ["uuid:f2a6eb41-5fc2-44a5-96d7-2cc3b27c41ad"],
        "name": "Supertypes",
        "location": "test/references/eClassifiers/Plant/inheritance.html#uuid-f2a6eb41-5fc2-44a5-96d7-2cc3b27c41ad",
        "type": {
            "name": "Action",
            "ns-uri": "ecore://nasdanika.org/html/app"
        }
    },
    {
        "container": {
            "reference": "sections",
            "identifiers": ["uuid:c66c5ee7-378b-4e64-9040-74a29396307c"]
        },
        "identifiers": ["uuid:3c3aab6c-a6a1-40d7-bcc6-c6c8f9def7e8"],
        "name": "Subtypes",
        "location": "test/references/eClassifiers/Plant/inheritance.html#uuid-3c3aab6c-a6a1-40d7-bcc6-c6c8f9def7e8",
        "type": {
            "name": "Action",
            "ns-uri": "ecore://nasdanika.org/html/app"
        }
    },
    {
        "container": {
            "reference": "navigation",
            "identifiers": ["uuid:5261066d-12d4-4c76-953a-55d2723224af"]
        },
        "identifiers": ["uuid:c4439d0c-75ca-4e6e-a7de-22e8f23eef8c"],
        "name": "Operations",
        "icon": "https://cdn.jsdelivr.net/gh/Nasdanika-Models/ecore@master/graph/web-resources/icons/EOperation.gif",
        "location": "test/references/eClassifiers/Plant/operations.html",
        "type": {
            "name": "Action",
            "ns-uri": "ecore://nasdanika.org/html/app"
        }
    },
    {
        "container": {
            "reference": "navigation",
            "identifiers": ["uuid:851d91a8-694e-43c6-b86c-141e6724aac9"]
        },
        "identifiers": ["uuid:e0aeaac9-a219-416a-9b62-1876bcb74fa9"],
        "name": "Classifiers",
        "location": "test/classifiers.html",
        "type": {
            "name": "Action",
            "ns-uri": "ecore://nasdanika.org/html/app"
        }
    }
]