[
    {
        "identifiers": ["uuid:cb33b056-7b91-43df-9738-4c46e7516abb"],
        "name": "Nasdanika",
        "icon": "https://docs.nasdanika.org/images/nasdanika-logo.png",
        "location": "https://www.nasdanika.org",
        "type": {
            "name": "Action",
            "ns-uri": "ecore://nasdanika.org/html/app"
        }
    },
    {
        "container": {
            "reference": "children",
            "identifiers": ["uuid:cb33b056-7b91-43df-9738-4c46e7516abb"]
        },
        "identifiers": ["uuid:48fd5233-815c-44d8-8fd0-24d8606c9b30"],
        "name": "Test Models Documentation",
        "icon": "fa fa-book",
        "location": "index.html",
        "type": {
            "name": "Action",
            "ns-uri": "ecore://nasdanika.org/html/app"
        }
    },
    {
        "container": {
            "reference": "children",
            "identifiers": ["uuid:cb33b056-7b91-43df-9738-4c46e7516abb"]
        },
        "identifiers": ["uuid:36f1ee62-294e-4d14-8f55-850a23560a44"],
        "name": "Search",
        "icon": "fas fa-search",
        "location": "search.html",
        "type": {
            "name": "Action",
            "ns-uri": "ecore://nasdanika.org/html/app"
        }
    },
    {
        "container": {
            "reference": "children",
            "identifiers": ["uuid:cb33b056-7b91-43df-9738-4c46e7516abb"]
        },
        "identifiers": ["uuid:4bfbfc78-4b44-4f10-be1a-d2fd287f0a35"],
        "name": "Glossary",
        "icon": "fas fa-book",
        "location": "glossary.html",
        "type": {
            "name": "Action",
            "ns-uri": "ecore://nasdanika.org/html/app"
        }
    },
    {
        "identifiers": ["ecore://test.ecore-gen.html.nasdanika.org"],
        "name": "Trum",
        "icon": "fas fa-users",
        "description": "My description",
        "location": "test/index.html",
        "type": {
            "name": "EPackage",
            "ns-uri": "http://www.eclipse.org/emf/2002/Ecore"
        }
    },
    {
        "container": {
            "reference": "eClassifiers",
            "identifiers": ["ecore://test.ecore-gen.html.nasdanika.org"]
        },
        "identifiers": ["ecore://test.ecore-gen.html.nasdanika.org/eClassifiers/Animal"],
        "name": "<i>Животное<\/i>",
        "icon": "https://cdn.jsdelivr.net/gh/Nasdanika-Models/ecore@master/graph/web-resources/icons/EClass.gif",
        "description": "Животные относятся к эукариотам (в клетках имеются ядра). Классическими признаками животных считаются: гетеротрофность (питание готовыми органическими соединениями) и способность активно передвигаться.",
        "location": "test/references/eClassifiers/Animal/index.html",
        "type": {
            "name": "EClass",
            "ns-uri": "http://www.eclipse.org/emf/2002/Ecore"
        }
    },
    {
        "container": {
            "reference": "navigation",
            "identifiers": ["uuid:0de3a043-8beb-4272-a94c-4c88994b540b"]
        },
        "identifiers": ["uuid:08119a37-50e6-4273-99d3-0caf07598711"],
        "name": "Attributes",
        "icon": "https://cdn.jsdelivr.net/gh/Nasdanika-Models/ecore@master/graph/web-resources/icons/EAttribute.gif",
        "location": "test/references/eClassifiers/Animal/attributes.html",
        "type": {
            "name": "Action",
            "ns-uri": "ecore://nasdanika.org/html/app"
        }
    },
    {
        "container": {
            "reference": "eStructuralFeatures",
            "identifiers": ["ecore://test.ecore-gen.html.nasdanika.org/eClassifiers/Animal"]
        },
        "identifiers": ["ecore://test.ecore-gen.html.nasdanika.org/eClassifiers/Animal/eStructuralFeatures/name"],
        "name": "Имя",
        "icon": "https://cdn.jsdelivr.net/gh/Nasdanika-Models/ecore@master/graph/web-resources/icons/EAttribute.gif",
        "description": "Имя животного, например 'Мурзик'",
        "location": "test/references/eClassifiers/Animal/references/eStructuralFeatures/name/index.html",
        "type": {
            "name": "EAttribute",
            "ns-uri": "http://www.eclipse.org/emf/2002/Ecore"
        }
    },
    {
        "container": {
            "reference": "navigation",
            "identifiers": ["uuid:bbf18c33-18a5-4475-bde9-40d389157923"]
        },
        "identifiers": ["uuid:7bd68408-46ac-4eb1-ac7f-0c027dc538b8"],
        "name": "Load specification",
        "location": "test/references/eClassifiers/Animal/references/eStructuralFeatures/name/load-specification.html",
        "type": {
            "name": "Action",
            "ns-uri": "ecore://nasdanika.org/html/app"
        }
    },
    {
        "container": {
            "reference": "navigation",
            "identifiers": ["uuid:0de3a043-8beb-4272-a94c-4c88994b540b"]
        },
        "identifiers": ["uuid:a89a52a4-fa82-4487-8503-b83d8cf8d653"],
        "name": "Inheritance",
        "icon": "https://cdn.jsdelivr.net/gh/Nasdanika-Models/ecore@master/graph/web-resources/icons/EGenericSuperType.gif",
        "location": "test/references/eClassifiers/Animal/inheritance.html",
        "type": {
            "name": "Action",
            "ns-uri": "ecore://nasdanika.org/html/app"
        }
    },
    {
        "container": {
            "reference": "sections",
            "identifiers": ["uuid:a89a52a4-fa82-4487-8503-b83d8cf8d653"]
        },
        "identifiers": ["uuid:21cda6f1-b900-4822-b7b0-d98fe7869ee7"],
        "name": "Supertypes",
        "location": "test/references/eClassifiers/Animal/inheritance.html#uuid-21cda6f1-b900-4822-b7b0-d98fe7869ee7",
        "type": {
            "name": "Action",
            "ns-uri": "ecore://nasdanika.org/html/app"
        }
    },
    {
        "container": {
            "reference": "sections",
            "identifiers": ["uuid:a89a52a4-fa82-4487-8503-b83d8cf8d653"]
        },
        "identifiers": ["uuid:63a4cf40-48bb-4da2-9d7b-379b6c0b840a"],
        "name": "Subtypes",
        "location": "test/references/eClassifiers/Animal/inheritance.html#uuid-63a4cf40-48bb-4da2-9d7b-379b6c0b840a",
        "type": {
            "name": "Action",
            "ns-uri": "ecore://nasdanika.org/html/app"
        }
    },
    {
        "container": {
            "reference": "navigation",
            "identifiers": ["uuid:0de3a043-8beb-4272-a94c-4c88994b540b"]
        },
        "identifiers": ["uuid:c170983d-dbdd-4c99-a3d9-65134f9448f0"],
        "name": "Operations",
        "icon": "https://cdn.jsdelivr.net/gh/Nasdanika-Models/ecore@master/graph/web-resources/icons/EOperation.gif",
        "location": "test/references/eClassifiers/Animal/operations.html",
        "type": {
            "name": "Action",
            "ns-uri": "ecore://nasdanika.org/html/app"
        }
    },
    {
        "container": {
            "reference": "eOperations",
            "identifiers": ["ecore://test.ecore-gen.html.nasdanika.org/eClassifiers/Animal"]
        },
        "identifiers": ["ecore://test.ecore-gen.html.nasdanika.org/eClassifiers/Animal/eOperations/eats"],
        "name": "Ест",
        "icon": "https://cdn.jsdelivr.net/gh/Nasdanika-Models/ecore@master/graph/web-resources/icons/EOperation.gif",
        "location": "test/references/eClassifiers/Animal/references/eOperations/eats-1/index.html",
        "type": {
            "name": "EOperation",
            "ns-uri": "http://www.eclipse.org/emf/2002/Ecore"
        }
    },
    {
        "container": {
            "reference": "navigation",
            "identifiers": ["uuid:27bbdfad-372d-41f7-9ea1-22b52969cee8"]
        },
        "identifiers": ["uuid:76c59e09-411f-4c5a-b3c2-e832776fd67a"],
        "name": "Parameters",
        "icon": "https://cdn.jsdelivr.net/gh/Nasdanika-Models/ecore@master/graph/web-resources/icons/EParameter.gif",
        "location": "test/references/eClassifiers/Animal/references/eOperations/eats-1/parameters.html",
        "type": {
            "name": "Action",
            "ns-uri": "ecore://nasdanika.org/html/app"
        }
    },
    {
        "container": {
            "reference": "eParameters",
            "identifiers": ["ecore://test.ecore-gen.html.nasdanika.org/eClassifiers/Animal/eOperations/eats"]
        },
        "identifiers": ["ecore://test.ecore-gen.html.nasdanika.org/eClassifiers/Animal/eOperations/eats/eParameters/food"],
        "name": "пища",
        "icon": "https://cdn.jsdelivr.net/gh/Nasdanika-Models/ecore@master/graph/web-resources/icons/EParameter.gif",
        "description": "Food which animal eats",
        "location": "test/references/eClassifiers/Animal/references/eOperations/eats-1/references/eParameters/food/index.html",
        "type": {
            "name": "EParameter",
            "ns-uri": "http://www.eclipse.org/emf/2002/Ecore"
        }
    },
    {
        "container": {
            "reference": "navigation",
            "identifiers": ["uuid:0de3a043-8beb-4272-a94c-4c88994b540b"]
        },
        "identifiers": ["uuid:f56f0ae3-2955-4e0b-ad07-471b5d6297b2"],
        "name": "Type Parameters",
        "icon": "https://cdn.jsdelivr.net/gh/Nasdanika-Models/ecore@master/graph/web-resources/icons/ETypeParameter.gif",
        "location": "test/references/eClassifiers/Animal/type-parameters.html",
        "type": {
            "name": "Action",
            "ns-uri": "ecore://nasdanika.org/html/app"
        }
    },
    {
        "container": {
            "reference": "eTypeParameters",
            "identifiers": ["ecore://test.ecore-gen.html.nasdanika.org/eClassifiers/Animal"]
        },
        "identifiers": ["ecore://test.ecore-gen.html.nasdanika.org/eClassifiers/Animal/eTypeParameters/F"],
        "name": "Пища",
        "icon": "https://cdn.jsdelivr.net/gh/Nasdanika-Models/ecore@master/graph/web-resources/icons/ETypeParameter.gif",
        "description": "Food which animal eats",
        "location": "test/references/eClassifiers/Animal/references/eTypeParameters/F/index.html",
        "type": {
            "name": "ETypeParameter",
            "ns-uri": "http://www.eclipse.org/emf/2002/Ecore"
        }
    },
    {
        "container": {
            "reference": "navigation",
            "identifiers": ["uuid:94fe3f98-8f38-4033-bf7e-67f04cf3dff8"]
        },
        "identifiers": ["uuid:caa576b7-4db3-4c2e-bdeb-99ad25c1311a"],
        "name": "Bounds",
        "icon": "https://cdn.jsdelivr.net/gh/Nasdanika-Models/ecore@master/graph/web-resources/icons/EGenericType.gif",
        "location": "test/references/eClassifiers/Animal/references/eTypeParameters/F/bounds.html",
        "type": {
            "name": "Action",
            "ns-uri": "ecore://nasdanika.org/html/app"
        }
    },
    {
        "container": {
            "reference": "eBounds",
            "identifiers": ["ecore://test.ecore-gen.html.nasdanika.org/eClassifiers/Animal/eTypeParameters/F"]
        },
        "identifiers": ["ecore://test.ecore-gen.html.nasdanika.org/eClassifiers/Animal/eTypeParameters/F/e-bounds/0"],
        "name": "Hmmm",
        "description": "Hmmm description",
        "location": "test/references/eClassifiers/Animal/references/eTypeParameters/F/references/eBounds/0/index.html",
        "type": {
            "name": "EGenericType",
            "ns-uri": "http://www.eclipse.org/emf/2002/Ecore"
        }
    },
    {
        "container": {
            "reference": "eClassifiers",
            "identifiers": ["ecore://test.ecore-gen.html.nasdanika.org"]
        },
        "identifiers": ["ecore://test.ecore-gen.html.nasdanika.org/eClassifiers/Biome"],
        "name": "<i>Biome<\/i>",
        "icon": "https://cdn.jsdelivr.net/gh/Nasdanika-Models/ecore@master/graph/web-resources/icons/EClass.gif",
        "location": "test/references/eClassifiers/Biome/index.html",
        "type": {
            "name": "EClass",
            "ns-uri": "http://www.eclipse.org/emf/2002/Ecore"
        }
    },
    {
        "container": {
            "reference": "navigation",
            "identifiers": ["uuid:e3ce0620-cd2e-4b52-9e6e-1604ed555176"]
        },
        "identifiers": ["uuid:e4bb7cb5-913e-4d08-b0ff-41a5311d369f"],
        "name": "References",
        "icon": "https://cdn.jsdelivr.net/gh/Nasdanika-Models/ecore@master/graph/web-resources/icons/EReference.gif",
        "location": "test/references/eClassifiers/Biome/references.html",
        "type": {
            "name": "Action",
            "ns-uri": "ecore://nasdanika.org/html/app"
        }
    },
    {
        "container": {
            "reference": "navigation",
            "identifiers": ["uuid:e3ce0620-cd2e-4b52-9e6e-1604ed555176"]
        },
        "identifiers": ["uuid:e3cd5eb7-8aa6-4ac6-9387-f0d01dc89ea1"],
        "name": "Inheritance",
        "icon": "https://cdn.jsdelivr.net/gh/Nasdanika-Models/ecore@master/graph/web-resources/icons/EGenericSuperType.gif",
        "location": "test/references/eClassifiers/Biome/inheritance.html",
        "type": {
            "name": "Action",
            "ns-uri": "ecore://nasdanika.org/html/app"
        }
    },
    {
        "container": {
            "reference": "sections",
            "identifiers": ["uuid:e3cd5eb7-8aa6-4ac6-9387-f0d01dc89ea1"]
        },
        "identifiers": ["uuid:841d6263-d2f1-4aae-a256-93d5338de08a"],
        "name": "Subtypes",
        "location": "test/references/eClassifiers/Biome/inheritance.html#uuid-841d6263-d2f1-4aae-a256-93d5338de08a",
        "type": {
            "name": "Action",
            "ns-uri": "ecore://nasdanika.org/html/app"
        }
    },
    {
        "container": {
            "reference": "eClassifiers",
            "identifiers": ["ecore://test.ecore-gen.html.nasdanika.org"]
        },
        "identifiers": ["ecore://test.ecore-gen.html.nasdanika.org/eClassifiers/Color"],
        "name": "Цвет",
        "icon": "https://cdn.jsdelivr.net/gh/Nasdanika-Models/ecore@master/graph/web-resources/icons/EEnum.gif",
        "description": "Цвет животного",
        "location": "test/references/eClassifiers/Color/index.html",
        "type": {
            "name": "EEnum",
            "ns-uri": "http://www.eclipse.org/emf/2002/Ecore"
        }
    },
    {
        "container": {
            "reference": "eLiterals",
            "identifiers": ["ecore://test.ecore-gen.html.nasdanika.org/eClassifiers/Color"]
        },
        "identifiers": ["ecore://test.ecore-gen.html.nasdanika.org/eClassifiers/Color/eLiterals/White"],
        "name": "Белый",
        "icon": "https://cdn.jsdelivr.net/gh/Nasdanika-Models/ecore@master/graph/web-resources/icons/EEnumLiteral.gif",
        "description": "White color",
        "location": "test/references/eClassifiers/Color/references/eLiterals/White/index.html",
        "type": {
            "name": "EEnumLiteral",
            "ns-uri": "http://www.eclipse.org/emf/2002/Ecore"
        }
    },
    {
        "container": {
            "reference": "eClassifiers",
            "identifiers": ["ecore://test.ecore-gen.html.nasdanika.org"]
        },
        "identifiers": ["ecore://test.ecore-gen.html.nasdanika.org/eClassifiers/Food"],
        "name": "<i>Food<\/i>",
        "icon": "https://cdn.jsdelivr.net/gh/Nasdanika-Models/ecore@master/graph/web-resources/icons/EInterface.gif",
        "location": "test/references/eClassifiers/Food/index.html",
        "type": {
            "name": "EClass",
            "ns-uri": "http://www.eclipse.org/emf/2002/Ecore"
        }
    },
    {
        "container": {
            "reference": "navigation",
            "identifiers": ["uuid:dbc88a7d-5300-4ba0-8360-8674a16de84b"]
        },
        "identifiers": ["uuid:82454d05-b704-4ec6-852b-9b89edaaa597"],
        "name": "Inheritance",
        "icon": "https://cdn.jsdelivr.net/gh/Nasdanika-Models/ecore@master/graph/web-resources/icons/EGenericSuperType.gif",
        "location": "test/references/eClassifiers/Food/inheritance.html",
        "type": {
            "name": "Action",
            "ns-uri": "ecore://nasdanika.org/html/app"
        }
    },
    {
        "container": {
            "reference": "sections",
            "identifiers": ["uuid:82454d05-b704-4ec6-852b-9b89edaaa597"]
        },
        "identifiers": ["uuid:8805f08d-4558-4faa-a7de-3aa1b20c0250"],
        "name": "Subtypes",
        "location": "test/references/eClassifiers/Food/inheritance.html#uuid-8805f08d-4558-4faa-a7de-3aa1b20c0250",
        "type": {
            "name": "Action",
            "ns-uri": "ecore://nasdanika.org/html/app"
        }
    },
    {
        "container": {
            "reference": "eClassifiers",
            "identifiers": ["ecore://test.ecore-gen.html.nasdanika.org"]
        },
        "identifiers": ["ecore://test.ecore-gen.html.nasdanika.org/eClassifiers/Forest"],
        "name": "Forest",
        "icon": "https://cdn.jsdelivr.net/gh/Nasdanika-Models/ecore@master/graph/web-resources/icons/EClass.gif",
        "location": "test/references/eClassifiers/Forest/index.html",
        "type": {
            "name": "EClass",
            "ns-uri": "http://www.eclipse.org/emf/2002/Ecore"
        }
    },
    {
        "container": {
            "reference": "navigation",
            "identifiers": ["uuid:5e2ad452-327c-49dd-85c1-135266cd587d"]
        },
        "identifiers": ["uuid:a1decd97-235c-4caf-891d-6a12dd9cff71"],
        "name": "Inheritance",
        "icon": "https://cdn.jsdelivr.net/gh/Nasdanika-Models/ecore@master/graph/web-resources/icons/EGenericSuperType.gif",
        "location": "test/references/eClassifiers/Forest/inheritance.html",
        "type": {
            "name": "Action",
            "ns-uri": "ecore://nasdanika.org/html/app"
        }
    },
    {
        "container": {
            "reference": "sections",
            "identifiers": ["uuid:a1decd97-235c-4caf-891d-6a12dd9cff71"]
        },
        "identifiers": ["uuid:676b9c34-354b-4bc5-8d4b-0a0ca69ef1eb"],
        "name": "Supertypes",
        "location": "test/references/eClassifiers/Forest/inheritance.html#uuid-676b9c34-354b-4bc5-8d4b-0a0ca69ef1eb",
        "type": {
            "name": "Action",
            "ns-uri": "ecore://nasdanika.org/html/app"
        }
    },
    {
        "container": {
            "reference": "navigation",
            "identifiers": ["uuid:5e2ad452-327c-49dd-85c1-135266cd587d"]
        },
        "identifiers": ["uuid:5578c8ef-7dce-47c6-b914-c31e91caf26e"],
        "name": "References",
        "icon": "https://cdn.jsdelivr.net/gh/Nasdanika-Models/ecore@master/graph/web-resources/icons/EReference.gif",
        "location": "test/references/eClassifiers/Forest/references.html",
        "type": {
            "name": "Action",
            "ns-uri": "ecore://nasdanika.org/html/app"
        }
    },
    {
        "container": {
            "reference": "navigation",
            "identifiers": ["uuid:5e2ad452-327c-49dd-85c1-135266cd587d"]
        },
        "identifiers": ["uuid:6c83e5c8-68f3-4470-8b3b-763149a5a7d0"],
        "name": "Load specification",
        "location": "test/references/eClassifiers/Forest/load-specification.html",
        "type": {
            "name": "Action",
            "ns-uri": "ecore://nasdanika.org/html/app"
        }
    },
    {
        "container": {
            "reference": "eClassifiers",
            "identifiers": ["ecore://test.ecore-gen.html.nasdanika.org"]
        },
        "identifiers": ["ecore://test.ecore-gen.html.nasdanika.org/eClassifiers/Fox"],
        "name": "Лиса",
        "icon": "https://img.icons8.com/fluency-systems-regular/16/fox.svg",
        "description": "Полифилетическая группа млекопитающих из семейства псовых отряда хищных",
        "location": "test/references/eClassifiers/Fox/index.html",
        "type": {
            "name": "EClass",
            "ns-uri": "http://www.eclipse.org/emf/2002/Ecore"
        }
    },
    {
        "container": {
            "reference": "navigation",
            "identifiers": ["uuid:8af4e0d8-18d2-4540-bb46-3993912d29ad"]
        },
        "identifiers": ["uuid:8ba10553-cec4-4c10-ae96-b38bab6cc8ac"],
        "name": "Attributes",
        "icon": "https://cdn.jsdelivr.net/gh/Nasdanika-Models/ecore@master/graph/web-resources/icons/EAttribute.gif",
        "location": "test/references/eClassifiers/Fox/attributes.html",
        "type": {
            "name": "Action",
            "ns-uri": "ecore://nasdanika.org/html/app"
        }
    },
    {
        "container": {
            "reference": "navigation",
            "identifiers": ["uuid:8af4e0d8-18d2-4540-bb46-3993912d29ad"]
        },
        "identifiers": ["uuid:9ba535cc-2fec-43c7-895c-36158ec46124"],
        "name": "Inheritance",
        "icon": "https://cdn.jsdelivr.net/gh/Nasdanika-Models/ecore@master/graph/web-resources/icons/EGenericSuperType.gif",
        "location": "test/references/eClassifiers/Fox/inheritance.html",
        "type": {
            "name": "Action",
            "ns-uri": "ecore://nasdanika.org/html/app"
        }
    },
    {
        "container": {
            "reference": "sections",
            "identifiers": ["uuid:9ba535cc-2fec-43c7-895c-36158ec46124"]
        },
        "identifiers": ["uuid:e6d30c76-2b3b-4f10-ab39-7e8b7f37edde"],
        "name": "Supertypes",
        "location": "test/references/eClassifiers/Fox/inheritance.html#uuid-e6d30c76-2b3b-4f10-ab39-7e8b7f37edde",
        "type": {
            "name": "Action",
            "ns-uri": "ecore://nasdanika.org/html/app"
        }
    },
    {
        "container": {
            "reference": "navigation",
            "identifiers": ["uuid:8af4e0d8-18d2-4540-bb46-3993912d29ad"]
        },
        "identifiers": ["uuid:3d652d18-99cf-41fe-9237-b8b795a746ed"],
        "name": "Operations",
        "icon": "https://cdn.jsdelivr.net/gh/Nasdanika-Models/ecore@master/graph/web-resources/icons/EOperation.gif",
        "location": "test/references/eClassifiers/Fox/operations.html",
        "type": {
            "name": "Action",
            "ns-uri": "ecore://nasdanika.org/html/app"
        }
    },
    {
        "container": {
            "reference": "navigation",
            "identifiers": ["uuid:8af4e0d8-18d2-4540-bb46-3993912d29ad"]
        },
        "identifiers": ["uuid:099a5243-411f-4bca-bbf7-4c2ef9566bd5"],
        "name": "Load specification",
        "location": "test/references/eClassifiers/Fox/load-specification.html",
        "type": {
            "name": "Action",
            "ns-uri": "ecore://nasdanika.org/html/app"
        }
    },
    {
        "container": {
            "reference": "eClassifiers",
            "identifiers": ["ecore://test.ecore-gen.html.nasdanika.org"]
        },
        "identifiers": ["ecore://test.ecore-gen.html.nasdanika.org/eClassifiers/Grass"],
        "name": "Grass",
        "icon": "https://cdn.jsdelivr.net/gh/Nasdanika-Models/ecore@master/graph/web-resources/icons/EClass.gif",
        "location": "test/references/eClassifiers/Grass/index.html",
        "type": {
            "name": "EClass",
            "ns-uri": "http://www.eclipse.org/emf/2002/Ecore"
        }
    },
    {
        "container": {
            "reference": "navigation",
            "identifiers": ["uuid:2c65d104-9d79-4552-93eb-3da309969319"]
        },
        "identifiers": ["uuid:92eb92bd-177e-40d7-9c32-c3f1ad03aa9f"],
        "name": "Attributes",
        "icon": "https://cdn.jsdelivr.net/gh/Nasdanika-Models/ecore@master/graph/web-resources/icons/EAttribute.gif",
        "location": "test/references/eClassifiers/Grass/attributes.html",
        "type": {
            "name": "Action",
            "ns-uri": "ecore://nasdanika.org/html/app"
        }
    },
    {
        "container": {
            "reference": "navigation",
            "identifiers": ["uuid:2c65d104-9d79-4552-93eb-3da309969319"]
        },
        "identifiers": ["uuid:b5f4c2c6-2dcb-4818-9f47-db5dea4631f5"],
        "name": "Inheritance",
        "icon": "https://cdn.jsdelivr.net/gh/Nasdanika-Models/ecore@master/graph/web-resources/icons/EGenericSuperType.gif",
        "location": "test/references/eClassifiers/Grass/inheritance.html",
        "type": {
            "name": "Action",
            "ns-uri": "ecore://nasdanika.org/html/app"
        }
    },
    {
        "container": {
            "reference": "sections",
            "identifiers": ["uuid:b5f4c2c6-2dcb-4818-9f47-db5dea4631f5"]
        },
        "identifiers": ["uuid:45121beb-a685-4719-bb4d-540efe6d031b"],
        "name": "Supertypes",
        "location": "test/references/eClassifiers/Grass/inheritance.html#uuid-45121beb-a685-4719-bb4d-540efe6d031b",
        "type": {
            "name": "Action",
            "ns-uri": "ecore://nasdanika.org/html/app"
        }
    },
    {
        "container": {
            "reference": "navigation",
            "identifiers": ["uuid:2c65d104-9d79-4552-93eb-3da309969319"]
        },
        "identifiers": ["uuid:80825774-3500-4de9-963b-370101bf66b8"],
        "name": "Operations",
        "icon": "https://cdn.jsdelivr.net/gh/Nasdanika-Models/ecore@master/graph/web-resources/icons/EOperation.gif",
        "location": "test/references/eClassifiers/Grass/operations.html",
        "type": {
            "name": "Action",
            "ns-uri": "ecore://nasdanika.org/html/app"
        }
    },
    {
        "container": {
            "reference": "navigation",
            "identifiers": ["uuid:2c65d104-9d79-4552-93eb-3da309969319"]
        },
        "identifiers": ["uuid:ded7d983-a404-40da-8e22-227374fefd5a"],
        "name": "Load specification",
        "location": "test/references/eClassifiers/Grass/load-specification.html",
        "type": {
            "name": "Action",
            "ns-uri": "ecore://nasdanika.org/html/app"
        }
    },
    {
        "container": {
            "reference": "eClassifiers",
            "identifiers": ["ecore://test.ecore-gen.html.nasdanika.org"]
        },
        "identifiers": ["ecore://test.ecore-gen.html.nasdanika.org/eClassifiers/Hare"],
        "name": "Зайка",
        "icon": "https://img.icons8.com/fluency-systems-regular/16/rabbit.svg",
        "description": "Зайка-попрыгайка",
        "location": "test/references/eClassifiers/Hare/index.html",
        "type": {
            "name": "EClass",
            "ns-uri": "http://www.eclipse.org/emf/2002/Ecore"
        }
    },
    {
        "container": {
            "reference": "navigation",
            "identifiers": ["uuid:c7bc15f4-ce75-41e7-b2d0-845885c16f1f"]
        },
        "identifiers": ["uuid:fc306188-3989-4fde-b1c7-2de7b16be135"],
        "name": "Attributes",
        "icon": "https://cdn.jsdelivr.net/gh/Nasdanika-Models/ecore@master/graph/web-resources/icons/EAttribute.gif",
        "location": "test/references/eClassifiers/Hare/attributes.html",
        "type": {
            "name": "Action",
            "ns-uri": "ecore://nasdanika.org/html/app"
        }
    },
    {
        "container": {
            "reference": "navigation",
            "identifiers": ["uuid:c7bc15f4-ce75-41e7-b2d0-845885c16f1f"]
        },
        "identifiers": ["uuid:b8a7609f-2278-4788-ad90-ee227a8d42f5"],
        "name": "Inheritance",
        "icon": "https://cdn.jsdelivr.net/gh/Nasdanika-Models/ecore@master/graph/web-resources/icons/EGenericSuperType.gif",
        "location": "test/references/eClassifiers/Hare/inheritance.html",
        "type": {
            "name": "Action",
            "ns-uri": "ecore://nasdanika.org/html/app"
        }
    },
    {
        "container": {
            "reference": "sections",
            "identifiers": ["uuid:b8a7609f-2278-4788-ad90-ee227a8d42f5"]
        },
        "identifiers": ["uuid:ff4d29ea-d7f6-4b83-a79b-551b4864e654"],
        "name": "Supertypes",
        "location": "test/references/eClassifiers/Hare/inheritance.html#uuid-ff4d29ea-d7f6-4b83-a79b-551b4864e654",
        "type": {
            "name": "Action",
            "ns-uri": "ecore://nasdanika.org/html/app"
        }
    },
    {
        "container": {
            "reference": "navigation",
            "identifiers": ["uuid:c7bc15f4-ce75-41e7-b2d0-845885c16f1f"]
        },
        "identifiers": ["uuid:f4f22fba-6528-4c63-b60a-98dcebf6ed6c"],
        "name": "Operations",
        "icon": "https://cdn.jsdelivr.net/gh/Nasdanika-Models/ecore@master/graph/web-resources/icons/EOperation.gif",
        "location": "test/references/eClassifiers/Hare/operations.html",
        "type": {
            "name": "Action",
            "ns-uri": "ecore://nasdanika.org/html/app"
        }
    },
    {
        "container": {
            "reference": "navigation",
            "identifiers": ["uuid:c7bc15f4-ce75-41e7-b2d0-845885c16f1f"]
        },
        "identifiers": ["uuid:4c8c1d73-fb45-41b3-bf7b-c1e97a85f5ab"],
        "name": "Load specification",
        "location": "test/references/eClassifiers/Hare/load-specification.html",
        "type": {
            "name": "Action",
            "ns-uri": "ecore://nasdanika.org/html/app"
        }
    },
    {
        "container": {
            "reference": "eClassifiers",
            "identifiers": ["ecore://test.ecore-gen.html.nasdanika.org"]
        },
        "identifiers": ["ecore://test.ecore-gen.html.nasdanika.org/eClassifiers/LivingBeing"],
        "name": "<i>LivingBeing<\/i>",
        "icon": "https://cdn.jsdelivr.net/gh/Nasdanika-Models/ecore@master/graph/web-resources/icons/EInterface.gif",
        "location": "test/references/eClassifiers/LivingBeing/index.html",
        "type": {
            "name": "EClass",
            "ns-uri": "http://www.eclipse.org/emf/2002/Ecore"
        }
    },
    {
        "container": {
            "reference": "navigation",
            "identifiers": ["uuid:35ea70f8-0344-4ded-b1f0-e51d2da921b2"]
        },
        "identifiers": ["uuid:5625c490-d3ab-4028-bacf-e92e7cca908f"],
        "name": "Attributes",
        "icon": "https://cdn.jsdelivr.net/gh/Nasdanika-Models/ecore@master/graph/web-resources/icons/EAttribute.gif",
        "location": "test/references/eClassifiers/LivingBeing/attributes.html",
        "type": {
            "name": "Action",
            "ns-uri": "ecore://nasdanika.org/html/app"
        }
    },
    {
        "container": {
            "reference": "navigation",
            "identifiers": ["uuid:35ea70f8-0344-4ded-b1f0-e51d2da921b2"]
        },
        "identifiers": ["uuid:fa14c3ed-9f0d-4995-946f-92c6873a777b"],
        "name": "Operations",
        "icon": "https://cdn.jsdelivr.net/gh/Nasdanika-Models/ecore@master/graph/web-resources/icons/EOperation.gif",
        "location": "test/references/eClassifiers/LivingBeing/operations.html",
        "type": {
            "name": "Action",
            "ns-uri": "ecore://nasdanika.org/html/app"
        }
    },
    {
        "container": {
            "reference": "navigation",
            "identifiers": ["uuid:35ea70f8-0344-4ded-b1f0-e51d2da921b2"]
        },
        "identifiers": ["uuid:4707d336-359d-4995-9e42-2209c80b2022"],
        "name": "Inheritance",
        "icon": "https://cdn.jsdelivr.net/gh/Nasdanika-Models/ecore@master/graph/web-resources/icons/EGenericSuperType.gif",
        "location": "test/references/eClassifiers/LivingBeing/inheritance.html",
        "type": {
            "name": "Action",
            "ns-uri": "ecore://nasdanika.org/html/app"
        }
    },
    {
        "container": {
            "reference": "sections",
            "identifiers": ["uuid:4707d336-359d-4995-9e42-2209c80b2022"]
        },
        "identifiers": ["uuid:d208043c-04c5-4370-8aa4-668c4fcd1d42"],
        "name": "Subtypes",
        "location": "test/references/eClassifiers/LivingBeing/inheritance.html#uuid-d208043c-04c5-4370-8aa4-668c4fcd1d42",
        "type": {
            "name": "Action",
            "ns-uri": "ecore://nasdanika.org/html/app"
        }
    },
    {
        "container": {
            "reference": "eClassifiers",
            "identifiers": ["ecore://test.ecore-gen.html.nasdanika.org"]
        },
        "identifiers": ["ecore://test.ecore-gen.html.nasdanika.org/eClassifiers/Plant"],
        "name": "Plant",
        "icon": "https://cdn.jsdelivr.net/gh/Nasdanika-Models/ecore@master/graph/web-resources/icons/EClass.gif",
        "location": "test/references/eClassifiers/Plant/index.html",
        "type": {
            "name": "EClass",
            "ns-uri": "http://www.eclipse.org/emf/2002/Ecore"
        }
    },
    {
        "container": {
            "reference": "navigation",
            "identifiers": ["uuid:069466c1-e623-4fa2-a89a-c9f60539987c"]
        },
        "identifiers": ["uuid:2ab4b6a3-cd77-4458-8e0b-d29fc98eca0c"],
        "name": "Attributes",
        "icon": "https://cdn.jsdelivr.net/gh/Nasdanika-Models/ecore@master/graph/web-resources/icons/EAttribute.gif",
        "location": "test/references/eClassifiers/Plant/attributes.html",
        "type": {
            "name": "Action",
            "ns-uri": "ecore://nasdanika.org/html/app"
        }
    },
    {
        "container": {
            "reference": "navigation",
            "identifiers": ["uuid:069466c1-e623-4fa2-a89a-c9f60539987c"]
        },
        "identifiers": ["uuid:2e26afd2-6a98-44c3-81f7-b657e07ea31d"],
        "name": "Inheritance",
        "icon": "https://cdn.jsdelivr.net/gh/Nasdanika-Models/ecore@master/graph/web-resources/icons/EGenericSuperType.gif",
        "location": "test/references/eClassifiers/Plant/inheritance.html",
        "type": {
            "name": "Action",
            "ns-uri": "ecore://nasdanika.org/html/app"
        }
    },
    {
        "container": {
            "reference": "sections",
            "identifiers": ["uuid:2e26afd2-6a98-44c3-81f7-b657e07ea31d"]
        },
        "identifiers": ["uuid:35aaec2e-85f7-42a0-aa66-6ca65a1aa16e"],
        "name": "Supertypes",
        "location": "test/references/eClassifiers/Plant/inheritance.html#uuid-35aaec2e-85f7-42a0-aa66-6ca65a1aa16e",
        "type": {
            "name": "Action",
            "ns-uri": "ecore://nasdanika.org/html/app"
        }
    },
    {
        "container": {
            "reference": "sections",
            "identifiers": ["uuid:2e26afd2-6a98-44c3-81f7-b657e07ea31d"]
        },
        "identifiers": ["uuid:ed867c55-1766-4ae2-a6ef-dd40fe82c2f7"],
        "name": "Subtypes",
        "location": "test/references/eClassifiers/Plant/inheritance.html#uuid-ed867c55-1766-4ae2-a6ef-dd40fe82c2f7",
        "type": {
            "name": "Action",
            "ns-uri": "ecore://nasdanika.org/html/app"
        }
    },
    {
        "container": {
            "reference": "navigation",
            "identifiers": ["uuid:069466c1-e623-4fa2-a89a-c9f60539987c"]
        },
        "identifiers": ["uuid:0af56196-006a-46c5-975a-414269805cf0"],
        "name": "Operations",
        "icon": "https://cdn.jsdelivr.net/gh/Nasdanika-Models/ecore@master/graph/web-resources/icons/EOperation.gif",
        "location": "test/references/eClassifiers/Plant/operations.html",
        "type": {
            "name": "Action",
            "ns-uri": "ecore://nasdanika.org/html/app"
        }
    },
    {
        "container": {
            "reference": "navigation",
            "identifiers": ["uuid:069466c1-e623-4fa2-a89a-c9f60539987c"]
        },
        "identifiers": ["uuid:a33979e9-edde-4077-9dea-cd2e40c232c8"],
        "name": "Load specification",
        "location": "test/references/eClassifiers/Plant/load-specification.html",
        "type": {
            "name": "Action",
            "ns-uri": "ecore://nasdanika.org/html/app"
        }
    },
    {
        "container": {
            "reference": "navigation",
            "identifiers": ["uuid:1ba40e5a-d796-4df1-8c45-5f09f0252f60"]
        },
        "identifiers": ["uuid:9417fb4c-c6c9-4cc0-8fe2-f66612ce0817"],
        "name": "Classifiers",
        "location": "test/classifiers.html",
        "type": {
            "name": "Action",
            "ns-uri": "ecore://nasdanika.org/html/app"
        }
    }
]